Workbook

Sheet Assumptions
A1: LBO Model – Key Assumptions
A3: Transaction Summary
A4: Total Purchase Price ($mm) | B4: 100
A5: Debt Financing ($mm) | B5: 70
A6: Equity Contribution ($mm) | B6: 30
A7: Leverage Ratio (Debt / Purchase) | B7: =B5/B4 -> 0.7
A8: Equity Ratio (Equity / Purchase) | B8: =B6/B4 -> 0.3
A10: Operating Assumptions
A11: Base EBITDA ($mm) | B11: 20
A12: EBITDA at Exit – Year 5 ($mm) | B12: 22
A13: Exit Multiple | B13: 6
A14: Investment Horizon (Years) | B14: 5
A16: Debt Assumptions
A17: Interest Rate | B17: 0.1
A18: Annual Principal Repayment ($mm) | B18: 10
A20: Derived Metrics
A21: Entry EV / EBITDA Multiple | B21: =B4/B11 -> 5
A22: Exit Enterprise Value ($mm) | B22: =B12*B13 -> 132

Sheet Debt Schedule
A1: Debt Repayment Schedule ($mm)
B3: At Close | C3: Year 1 | D3: Year 2 | E3: Year 3 | F3: Year 4 | G3: Year 5
A4: Beginning Debt Balance | B4: =Assumptions!B5 -> 70 | C4: =B6 -> 70 | D4: =C6 -> 60 | E4: =D6 -> 50 | F4: =E6 -> 40 | G4: =F6 -> 30
A5: Annual Principal Repayment | C5: =MIN(Assumptions!$B$18,C4) -> 10 | D5: =MIN(Assumptions!$B$18,D4) -> 10 | E5: =MIN(Assumptions!$B$18,E4) -> 10 | F5: =MIN(Assumptions!$B$18,F4) -> 10 | G5: =MIN(Assumptions!$B$18,G4) -> 10
A6: Ending Debt Balance | B6: =Assumptions!B5 -> 70 | C6: =C4-C5 -> 60 | D6: =D4-D5 -> 50 | E6: =E4-E5 -> 40 | F6: =F4-F5 -> 30 | G6: =G4-G5 -> 20
A8: Interest Expense (on Beg. Balance) | C8: =C4*Assumptions!$B$17 -> 7 | D8: =D4*Assumptions!$B$17 -> 6 | E8: =E4*Assumptions!$B$17 -> 5 | F8: =F4*Assumptions!$B$17 -> 4 | G8: =G4*Assumptions!$B$17 -> 3
A10: Total Debt Service (Principal + Interest) | C10: =C5+C8 -> 17 | D10: =D5+D8 -> 16 | E10: =E5+E8 -> 15 | F10: =F5+F8 -> 14 | G10: =G5+G8 -> 13
A12: Cumulative Principal Repaid | B12: 0 | C12: =B12+C5 -> 10 | D12: =C12+D5 -> 20 | E12: =D12+E5 -> 30 | F12: =E12+F5 -> 40 | G12: =F12+G5 -> 50

Sheet Returns Analysis
A1: LBO Returns Analysis
A3: Exit Valuation
A4: EBITDA at Exit (Year 5) ($mm) | B4: =Assumptions!B12 -> 22
A5: Exit Multiple | B5: =Assumptions!B13 -> 6
A6: Enterprise Value at Exit ($mm) | B6: =B4*B5 -> 132 | C6: EV = EBITDA × Exit Multiple
A8: Equity Value at Exit
A9: Enterprise Value at Exit ($mm) | B9: =B6 -> 132
A10: Less: Remaining Debt at Exit ($mm) | B10: ='Debt Schedule'!G6 -> 20 | C10: Ending balance Year 5
A11: Equity Value to Investors ($mm) | B11: =B9-B10 -> 112
A13: Investor Returns
A14: Initial Equity Investment ($mm) | B14: =Assumptions!B6 -> 30
A15: Equity Proceeds at Exit ($mm) | B15: =B11 -> 112
A16: Dollar Gain ($mm) | B16: =B15-B14 -> 82
A18: MOIC (Multiple of Invested Capital) | B18: =B15/B14 -> 3.7333333
A19: IRR (Internal Rate of Return) | B19: =(B15/B14)^(1/Assumptions!B14)-1 -> 0.30142562
A21: Return Drivers Summary
A22: Return from EBITDA Growth | B22: =(Assumptions!B12-Assumptions!B11)/Assumptions!B11 -> 0.1 | C22: EBITDA growth over hold period
A23: Total Debt Repaid ($mm) | B23: ='Debt Schedule'!G12 -> 50
A24: Total Interest Paid ($mm) | B24: =SUM('Debt Schedule'!C8:G8) -> 25

Sheet IRR Cash Flows
A1: IRR Calculation – Equity Cash Flows ($mm)
B3: Year 0 | C3: Year 1 | D3: Year 2 | E3: Year 3 | F3: Year 4 | G3: Year 5
A4: Equity Cash Flow ($mm) | B4: =-Assumptions!B6 -> -30 | C4: 0 | D4: 0 | E4: 0 | F4: 0 | G4: ='Returns Analysis'!B11 -> 112
A6: IRR (Excel IRR Function) | B6: =IRR(B4:G4) -> 0.30142562
A7: MOIC Check | B7: =G4/-B4 -> 3.7333333
