Workbook

Sheet Assumptions
B2: Toronto Condo Investment — 10-Year Financial Model
B3: All blue values are adjustable assumptions
B5: PURCHASE ASSUMPTIONS | E5: RESEARCH-BASED APPRECIATION JUSTIFICATION
B6: Purchase Price | C6: 1000000 | E6: Historical 25-Year CAGR (1996–2021) | F6: 7.1%
B7: Down Payment (%) | C7: 0.2 | E7: TRREB Q4 2025 GTA Avg Condo Price | F7: $652,945 (▼5.1% YoY)
B8: Down Payment ($) | C8: =C6*C7 -> 200000 | E8: TRREB Q4 2025 City of Toronto Avg | F8: $690,607 (▼3.5% YoY)
B9: Mortgage Amount (LTV) | C9: =C6-C8 -> 800000 | E9: CMHC 2026 Forecast (GTA condos) | F9: ▼4.5% YoY in Q4 2026
B10: Closing Costs (% of Purchase) | C10: 0.025 | E10: TD Economics 2025 GTA Condo Forecast | F10: ▼10% from peak
B11: Closing Costs ($) | C11: =C6*C10 -> 25000 | E11: RBC 2026 National Forecast | F11: ▼0.7% overall
B12: Total Cash Invested at Close | C12: =C8+C11 -> 225000 | E12: BMO Through 2027 Outlook | F12: ~3% annual price growth
E13: BoC Policy Rate (Jan 2026) | F13: 2.25% — expected stable
B14: MORTGAGE ASSUMPTIONS | E14: GTA Condo Vacancy Rate (Q2 2025) | F14: 3.2% City / 4.0% 905
B15: Annual Interest Rate | C15: 0.06 | E15: Avg Rent YoY Change (Q4 2025) | F15: ▼6.0%
B16: Amortization Period (Years) | C16: 30 | E16: New Condo Completions 2025 | F16: 31,422 (record high)
B17: Monthly Interest Rate | C17: =C15/12 -> 0.005 | E17: Condo Starts 2025 (annualized) | F17: Lowest since 1998
B18: Total Payments | C18: =C16*12 -> 360
B19: Monthly Mortgage Payment | C19: =-PMT(C17,C18,C9) -> 4796.4042 | E19: BASE CASE: 2.5% CAGR | F19: Recovery from trough; supply constraints emerge 2028+
B20: Annual Mortgage Payment | C20: =C19*12 -> 57556.85 | E20: BULL CASE: 4.0% CAGR | F20: Faster absorption; immigration reversal; rate cuts
E21: BEAR CASE: 0.5% CAGR | F21: Prolonged stagnation; investor exit; recession risk
B22: RENTAL ASSUMPTIONS
B23: Monthly Rent (Year 1) | C23: 4000 | E23: KEY SOURCES
B24: Annual Rent Escalation | C24: 0.025 | E24: TRREB Q4 2025 Condo Market Report
B25: Vacancy Rate | C25: 0.1 | E25: CMHC Housing Market Outlook 2026
B26: Operating Expenses (% of EGI) | C26: 0.25 | E26: TD Economics — GTA Condo Market Outlook
E27: RBC Economics — Housing Market Forecast
B28: APPRECIATION ASSUMPTIONS | E28: BMO Economics — Housing Outlook
B29: Base Case — Annual Appreciation | C29: 0.025 | E29: CIBC Capital Markets — Housing Analysis
B30: Bull Case — Annual Appreciation | C30: 0.04 | E30: CBRE Toronto Real Estate Outlook 2025
B31: Bear Case — Annual Appreciation | C31: 0.005 | E31: Urbanation — Completed Condo Inventory Data
E32: Bank of Canada — Policy Rate Decisions
B33: DISPOSITION ASSUMPTIONS | E33: Statistics Canada — Immigration & Housing
B34: Holding Period (Years) | C34: 10
B35: Disposition Costs (% of Sale Price) | C35: 0.05

Sheet 10-Year Model
B2: 10-Year Pro Forma — Base Case Analysis
C4: Year 0 | D4: Year 1 | E4: Year 2 | F4: Year 3 | G4: Year 4 | H4: Year 5 | I4: Year 6 | J4: Year 7 | K4: Year 8 | L4: Year 9 | M4: Year 10
B5: PROPERTY VALUE
B6: Appreciation Rate | D6: =Assumptions!C29 -> 0.025 | E6: =Assumptions!C29 -> 0.025 | F6: =Assumptions!C29 -> 0.025 | G6: =Assumptions!C29 -> 0.025 | H6: =Assumptions!C29 -> 0.025 | I6: =Assumptions!C29 -> 0.025 | J6: =Assumptions!C29 -> 0.025 | K6: =Assumptions!C29 -> 0.025 | L6: =Assumptions!C29 -> 0.025 | M6: =Assumptions!C29 -> 0.025
B7: Property Value (BOY) | C7: =Assumptions!C6 -> 1000000 | D7: =C7*(1+D6) -> 1025000 | E7: =D7*(1+E6) -> 1050625 | F7: =E7*(1+F6) -> 1076890.6 | G7: =F7*(1+G6) -> 1103812.9 | H7: =G7*(1+H6) -> 1131408.2 | I7: =H7*(1+I6) -> 1159693.4 | J7: =I7*(1+J6) -> 1188685.8 | K7: =J7*(1+K6) -> 1218402.9 | ... M7: =L7*(1+M6) -> 1280084.5
B9: RENTAL INCOME
B10: Monthly Rent | D10: =Assumptions!C23 -> 4000 | E10: =D10*(1+Assumptions!C24) -> 4100 | F10: =E10*(1+Assumptions!C24) -> 4202.5 | G10: =F10*(1+Assumptions!C24) -> 4307.5625 | H10: =G10*(1+Assumptions!C24) -> 4415.2516 | I10: =H10*(1+Assumptions!C24) -> 4525.6329 | J10: =I10*(1+Assumptions!C24) -> 4638.7737 | K10: =J10*(1+Assumptions!C24) -> 4754.743 | L10: =K10*(1+Assumptions!C24) -> 4873.6116 | M10: =L10*(1+Assumptions!C24) -> 4995.4519
B11: Gross Rental Income (Annual) | D11: =D10*12 -> 48000 | E11: =E10*12 -> 49200 | F11: =F10*12 -> 50430 | G11: =G10*12 -> 51690.75 | H11: =H10*12 -> 52983.019 | I11: =I10*12 -> 54307.594 | J11: =J10*12 -> 55665.284 | K11: =K10*12 -> 57056.916 | ... M11: =M10*12 -> 59945.423
B12: Less: Vacancy Loss | D12: =-D11*Assumptions!C25 -> -4800 | E12: =-E11*Assumptions!C25 -> -4920 | F12: =-F11*Assumptions!C25 -> -5043 | G12: =-G11*Assumptions!C25 -> -5169.075 | H12: =-H11*Assumptions!C25 -> -5298.3019 | I12: =-I11*Assumptions!C25 -> -5430.7594 | J12: =-J11*Assumptions!C25 -> -5566.5284 | K12: =-K11*Assumptions!C25 -> -5705.6916 | L12: =-L11*Assumptions!C25 -> -5848.3339 | M12: =-M11*Assumptions!C25 -> -5994.5423
B13: Effective Gross Income (EGI) | D13: =D11+D12 -> 43200 | E13: =E11+E12 -> 44280 | F13: =F11+F12 -> 45387 | G13: =G11+G12 -> 46521.675 | H13: =H11+H12 -> 47684.717 | I13: =I11+I12 -> 48876.835 | J13: =J11+J12 -> 50098.756 | K13: =K11+K12 -> 51351.225 | ... M13: =M11+M12 -> 53950.88
B15: OPERATING EXPENSES
B16: Operating Expenses (25% of EGI) | D16: =-D13*Assumptions!C26 -> -10800 | E16: =-E13*Assumptions!C26 -> -11070 | F16: =-F13*Assumptions!C26 -> -11346.75 | G16: =-G13*Assumptions!C26 -> -11630.419 | H16: =-H13*Assumptions!C26 -> -11921.179 | I16: =-I13*Assumptions!C26 -> -12219.209 | J16: =-J13*Assumptions!C26 -> -12524.689 | K16: =-K13*Assumptions!C26 -> -12837.806 | L16: =-L13*Assumptions!C26 -> -13158.751 | M16: =-M13*Assumptions!C26 -> -13487.72
B17: Net Operating Income (NOI) | D17: =D13+D16 -> 32400 | E17: =E13+E16 -> 33210 | F17: =F13+F16 -> 34040.25 | G17: =G13+G16 -> 34891.256 | H17: =H13+H16 -> 35763.538 | I17: =I13+I16 -> 36657.626 | J17: =J13+J16 -> 37574.067 | K17: =K13+K16 -> 38513.418 | ... M17: =M13+M16 -> 40463.16
B19: DEBT SERVICE
B20: Annual Mortgage Payment | D20: =-Assumptions!C20 -> -57556.85 | E20: =-Assumptions!C20 -> -57556.85 | F20: =-Assumptions!C20 -> -57556.85 | G20: =-Assumptions!C20 -> -57556.85 | H20: =-Assumptions!C20 -> -57556.85 | I20: =-Assumptions!C20 -> -57556.85 | J20: =-Assumptions!C20 -> -57556.85 | K20: =-Assumptions!C20 -> -57556.85 | L20: =-Assumptions!C20 -> -57556.85 | M20: =-Assumptions!C20 -> -57556.85
B21: Interest Portion | D21: =CUMIPMT(Assumptions!C17,Assumptions!C18,Assumptions!C9,(1-1)*12+1,1*12,0) -> -47732.757 | E21: =CUMIPMT(Assumptions!C17,Assumptions!C18,Assumptions!C9,(2-1)*12+1,2*12,0) -> -47126.828 | F21: =CUMIPMT(Assumptions!C17,Assumptions!C18,Assumptions!C9,(3-1)*12+1,3*12,0) -> -46483.527 | G21: =CUMIPMT(Assumptions!C17,Assumptions!C18,Assumptions!C9,(4-1)*12+1,4*12,0) -> -45800.549 | H21: =CUMIPMT(Assumptions!C17,Assumptions!C18,Assumptions!C9,(5-1)*12+1,5*12,0) -> -45075.446 | I21: =CUMIPMT(Assumptions!C17,Assumptions!C18,Assumptions!C9,(6-1)*12+1,6*12,0) -> -44305.62 | J21: =CUMIPMT(Assumptions!C17,Assumptions!C18,Assumptions!C9,(7-1)*12+1,7*12,0) -> -43488.313 | K21: =CUMIPMT(Assumptions!C17,Assumptions!C18,Assumptions!C9,(8-1)*12+1,8*12,0) -> -42620.597 | L21: =CUMIPMT(Assumptions!C17,Assumptions!C18,Assumptions!C9,(9-1)*12+1,9*12,0) -> -41699.361 | M21: =CUMIPMT(Assumptions!C17,Assumptions!C18,Assumptions!C9,(10-1)*12+1,10*12,0) -> -40721.306
B22: Principal Portion | D22: =CUMPRINC(Assumptions!C17,Assumptions!C18,Assumptions!C9,(1-1)*12+1,1*12,0) -> -9824.0937 | E22: =CUMPRINC(Assumptions!C17,Assumptions!C18,Assumptions!C9,(2-1)*12+1,2*12,0) -> -10430.022 | F22: =CUMPRINC(Assumptions!C17,Assumptions!C18,Assumptions!C9,(3-1)*12+1,3*12,0) -> -11073.323 | G22: =CUMPRINC(Assumptions!C17,Assumptions!C18,Assumptions!C9,(4-1)*12+1,4*12,0) -> -11756.302 | H22: =CUMPRINC(Assumptions!C17,Assumptions!C18,Assumptions!C9,(5-1)*12+1,5*12,0) -> -12481.405 | I22: =CUMPRINC(Assumptions!C17,Assumptions!C18,Assumptions!C9,(6-1)*12+1,6*12,0) -> -13251.23 | J22: =CUMPRINC(Assumptions!C17,Assumptions!C18,Assumptions!C9,(7-1)*12+1,7*12,0) -> -14068.537 | K22: =CUMPRINC(Assumptions!C17,Assumptions!C18,Assumptions!C9,(8-1)*12+1,8*12,0) -> -14936.254 | L22: =CUMPRINC(Assumptions!C17,Assumptions!C18,Assumptions!C9,(9-1)*12+1,9*12,0) -> -15857.489 | M22: =CUMPRINC(Assumptions!C17,Assumptions!C18,Assumptions!C9,(10-1)*12+1,10*12,0) -> -16835.544
B24: ANNUAL CASH FLOW
B25: Pre-Tax Cash Flow | C25: =-Assumptions!C12 -> -225000 | D25: =D17+D20 -> -25156.85 | E25: =E17+E20 -> -24346.85 | F25: =F17+F20 -> -23516.6 | G25: =G17+G20 -> -22665.594 | H25: =H17+H20 -> -21793.313 | I25: =I17+I20 -> -20899.224 | J25: =J17+J20 -> -19982.784 | K25: =K17+K20 -> -19043.432 | ... M25: =M17+M20 -> -17093.69
B26: Cumulative Cash Flow | C26: =C25 -> -225000 | D26: =C26+D25 -> -250156.85 | E26: =D26+E25 -> -274503.7 | F26: =E26+F25 -> -298020.3 | G26: =F26+G25 -> -320685.9 | H26: =G26+H25 -> -342479.21 | I26: =H26+I25 -> -363378.43 | J26: =I26+J25 -> -383361.22 | K26: =J26+K25 -> -402404.65 | ... M26: =L26+M25 -> -437578.93
B28: EQUITY BUILDUP
B29: Mortgage Balance Outstanding | C29: =Assumptions!C9 -> 800000 | D29: =C29+D22 -> 790175.91 | E29: =D29+E22 -> 779745.88 | F29: =E29+F22 -> 768672.56 | G29: =F29+G22 -> 756916.26 | H29: =G29+H22 -> 744434.85 | I29: =H29+I22 -> 731183.62 | J29: =I29+J22 -> 717115.09 | K29: =J29+K22 -> 702178.83 | ... M29: =L29+M22 -> 669485.8
B30: Equity from Principal Paydown | C30: =Assumptions!C8 -> 200000 | D30: =D7-D29 -> 234824.09 | E30: =E7-E29 -> 270879.12 | F30: =F7-F29 -> 308218.06 | G30: =G7-G29 -> 346896.63 | H30: =H7-H29 -> 386973.36 | I30: =I7-I29 -> 428509.79 | J30: =J7-J29 -> 471570.67 | K30: =K7-K29 -> 516224.06 | ... M30: =M7-M29 -> 610598.74
B31: Appreciation Gain (Cumulative) | C31: 0 | D31: =D7-Assumptions!C6 -> 25000 | E31: =E7-Assumptions!C6 -> 50625 | F31: =F7-Assumptions!C6 -> 76890.625 | G31: =G7-Assumptions!C6 -> 103812.89 | H31: =H7-Assumptions!C6 -> 131408.21 | I31: =I7-Assumptions!C6 -> 159693.42 | J31: =J7-Assumptions!C6 -> 188685.75 | K31: =K7-Assumptions!C6 -> 218402.9 | L31: =L7-Assumptions!C6 -> 248862.97 | M31: =M7-Assumptions!C6 -> 280084.54
B32: Total Equity | C32: =Assumptions!C8 -> 200000 | D32: =D7-D29 -> 234824.09 | E32: =E7-E29 -> 270879.12 | F32: =F7-F29 -> 308218.06 | G32: =G7-G29 -> 346896.63 | H32: =H7-H29 -> 386973.36 | I32: =I7-I29 -> 428509.79 | J32: =J7-J29 -> 471570.67 | K32: =K7-K29 -> 516224.06 | ... M32: =M7-M29 -> 610598.74
B34: DISPOSITION ANALYSIS (YEAR 10)
B35: Sale Price (Year 10 Value) | M35: =M7 -> 1280084.5
B36: Less: Disposition Costs | M36: =-M35*Assumptions!C35 -> -64004.227
B37: Less: Mortgage Payoff | M37: =-M29 -> -669485.8
B38: Net Sale Proceeds | M38: =M35+M36+M37 -> 546594.52
B40: RETURN METRICS
B41: Cash Flow for IRR | C41: =C25 -> -225000 | D41: =D25 -> -25156.85 | E41: =E25 -> -24346.85 | F41: =F25 -> -23516.6 | G41: =G25 -> -22665.594 | H41: =H25 -> -21793.313 | I41: =I25 -> -20899.224 | J41: =J25 -> -19982.784 | ... L41: =L25 -> -18080.597 | M41: =M25+M38 -> 529500.83
B42: IRR (Leveraged) | C42: =IRR(C41:M41) -> 0.029521862
B43: Total Profit | C43: =M38+M26-C25 -> 334015.58
B44: Equity Multiple | C44: =(M38+SUM(D25:M25))/(-C25) -> 1.4845137
B45: Cash-on-Cash Return (Year 1) | C45: =D25/(-C25) -> -0.11180822
B46: Cap Rate (Year 1) | C46: =D17/Assumptions!C6 -> 0.0324

Sheet Amortization
B2: Annual Mortgage Amortization Schedule
B4: Year | C4: Beg. Balance | D4: Annual Payment | E4: Interest | F4: Principal | G4: End Balance
B5: 1 | C5: =Assumptions!C9 -> 800000 | D5: =Assumptions!C20 -> 57556.85 | E5: =-CUMIPMT(Assumptions!C17,Assumptions!C18,Assumptions!C9,(1-1)*12+1,1*12,0) -> 47732.757 | F5: =-CUMPRINC(Assumptions!C17,Assumptions!C18,Assumptions!C9,(1-1)*12+1,1*12,0) -> 9824.0937 | G5: =C5-F5 -> 790175.91
B6: 2 | C6: =G5 -> 790175.91 | D6: =Assumptions!C20 -> 57556.85 | E6: =-CUMIPMT(Assumptions!C17,Assumptions!C18,Assumptions!C9,(2-1)*12+1,2*12,0) -> 47126.828 | F6: =-CUMPRINC(Assumptions!C17,Assumptions!C18,Assumptions!C9,(2-1)*12+1,2*12,0) -> 10430.022 | G6: =C6-F6 -> 779745.88
B7: 3 | C7: =G6 -> 779745.88 | D7: =Assumptions!C20 -> 57556.85 | E7: =-CUMIPMT(Assumptions!C17,Assumptions!C18,Assumptions!C9,(3-1)*12+1,3*12,0) -> 46483.527 | F7: =-CUMPRINC(Assumptions!C17,Assumptions!C18,Assumptions!C9,(3-1)*12+1,3*12,0) -> 11073.323 | G7: =C7-F7 -> 768672.56
B8: 4 | C8: =G7 -> 768672.56 | D8: =Assumptions!C20 -> 57556.85 | E8: =-CUMIPMT(Assumptions!C17,Assumptions!C18,Assumptions!C9,(4-1)*12+1,4*12,0) -> 45800.549 | F8: =-CUMPRINC(Assumptions!C17,Assumptions!C18,Assumptions!C9,(4-1)*12+1,4*12,0) -> 11756.302 | G8: =C8-F8 -> 756916.26
B9: 5 | C9: =G8 -> 756916.26 | D9: =Assumptions!C20 -> 57556.85 | E9: =-CUMIPMT(Assumptions!C17,Assumptions!C18,Assumptions!C9,(5-1)*12+1,5*12,0) -> 45075.446 | F9: =-CUMPRINC(Assumptions!C17,Assumptions!C18,Assumptions!C9,(5-1)*12+1,5*12,0) -> 12481.405 | G9: =C9-F9 -> 744434.85
B10: 6 | C10: =G9 -> 744434.85 | D10: =Assumptions!C20 -> 57556.85 | E10: =-CUMIPMT(Assumptions!C17,Assumptions!C18,Assumptions!C9,(6-1)*12+1,6*12,0) -> 44305.62 | F10: =-CUMPRINC(Assumptions!C17,Assumptions!C18,Assumptions!C9,(6-1)*12+1,6*12,0) -> 13251.23 | G10: =C10-F10 -> 731183.62
B11: 7 | C11: =G10 -> 731183.62 | D11: =Assumptions!C20 -> 57556.85 | E11: =-CUMIPMT(Assumptions!C17,Assumptions!C18,Assumptions!C9,(7-1)*12+1,7*12,0) -> 43488.313 | F11: =-CUMPRINC(Assumptions!C17,Assumptions!C18,Assumptions!C9,(7-1)*12+1,7*12,0) -> 14068.537 | G11: =C11-F11 -> 717115.09
B12: 8 | C12: =G11 -> 717115.09 | D12: =Assumptions!C20 -> 57556.85 | E12: =-CUMIPMT(Assumptions!C17,Assumptions!C18,Assumptions!C9,(8-1)*12+1,8*12,0) -> 42620.597 | F12: =-CUMPRINC(Assumptions!C17,Assumptions!C18,Assumptions!C9,(8-1)*12+1,8*12,0) -> 14936.254 | G12: =C12-F12 -> 702178.83
B13: 9 | C13: =G12 -> 702178.83 | D13: =Assumptions!C20 -> 57556.85 | E13: =-CUMIPMT(Assumptions!C17,Assumptions!C18,Assumptions!C9,(9-1)*12+1,9*12,0) -> 41699.361 | F13: =-CUMPRINC(Assumptions!C17,Assumptions!C18,Assumptions!C9,(9-1)*12+1,9*12,0) -> 15857.489 | G13: =C13-F13 -> 686321.34
B14: 10 | C14: =G13 -> 686321.34 | D14: =Assumptions!C20 -> 57556.85 | E14: =-CUMIPMT(Assumptions!C17,Assumptions!C18,Assumptions!C9,(10-1)*12+1,10*12,0) -> 40721.306 | F14: =-CUMPRINC(Assumptions!C17,Assumptions!C18,Assumptions!C9,(10-1)*12+1,10*12,0) -> 16835.544 | G14: =C14-F14 -> 669485.8
B15: 11 | C15: =G14 -> 669485.8 | D15: =Assumptions!C20 -> 57556.85 | E15: =-CUMIPMT(Assumptions!C17,Assumptions!C18,Assumptions!C9,(11-1)*12+1,11*12,0) -> 39682.926 | F15: =-CUMPRINC(Assumptions!C17,Assumptions!C18,Assumptions!C9,(11-1)*12+1,11*12,0) -> 17873.924 | G15: =C15-F15 -> 651611.88
B16: 12 | C16: =G15 -> 651611.88 | D16: =Assumptions!C20 -> 57556.85 | E16: =-CUMIPMT(Assumptions!C17,Assumptions!C18,Assumptions!C9,(12-1)*12+1,12*12,0) -> 38580.502 | F16: =-CUMPRINC(Assumptions!C17,Assumptions!C18,Assumptions!C9,(12-1)*12+1,12*12,0) -> 18976.349 | G16: =C16-F16 -> 632635.53
B17: 13 | C17: =G16 -> 632635.53 | D17: =Assumptions!C20 -> 57556.85 | E17: =-CUMIPMT(Assumptions!C17,Assumptions!C18,Assumptions!C9,(13-1)*12+1,13*12,0) -> 37410.082 | F17: =-CUMPRINC(Assumptions!C17,Assumptions!C18,Assumptions!C9,(13-1)*12+1,13*12,0) -> 20146.768 | G17: =C17-F17 -> 612488.76
B18: 14 | C18: =G17 -> 612488.76 | D18: =Assumptions!C20 -> 57556.85 | E18: =-CUMIPMT(Assumptions!C17,Assumptions!C18,Assumptions!C9,(14-1)*12+1,14*12,0) -> 36167.474 | F18: =-CUMPRINC(Assumptions!C17,Assumptions!C18,Assumptions!C9,(14-1)*12+1,14*12,0) -> 21389.377 | G18: =C18-F18 -> 591099.38
B19: 15 | C19: =G18 -> 591099.38 | D19: =Assumptions!C20 -> 57556.85 | E19: =-CUMIPMT(Assumptions!C17,Assumptions!C18,Assumptions!C9,(15-1)*12+1,15*12,0) -> 34848.224 | F19: =-CUMPRINC(Assumptions!C17,Assumptions!C18,Assumptions!C9,(15-1)*12+1,15*12,0) -> 22708.627 | G19: =C19-F19 -> 568390.76
B20: 16 | C20: =G19 -> 568390.76 | D20: =Assumptions!C20 -> 57556.85 | E20: =-CUMIPMT(Assumptions!C17,Assumptions!C18,Assumptions!C9,(16-1)*12+1,16*12,0) -> 33447.605 | F20: =-CUMPRINC(Assumptions!C17,Assumptions!C18,Assumptions!C9,(16-1)*12+1,16*12,0) -> 24109.245 | G20: =C20-F20 -> 544281.51
B21: 17 | C21: =G20 -> 544281.51 | D21: =Assumptions!C20 -> 57556.85 | E21: =-CUMIPMT(Assumptions!C17,Assumptions!C18,Assumptions!C9,(17-1)*12+1,17*12,0) -> 31960.6 | F21: =-CUMPRINC(Assumptions!C17,Assumptions!C18,Assumptions!C9,(17-1)*12+1,17*12,0) -> 25596.251 | G21: =C21-F21 -> 518685.26
B22: 18 | C22: =G21 -> 518685.26 | D22: =Assumptions!C20 -> 57556.85 | E22: =-CUMIPMT(Assumptions!C17,Assumptions!C18,Assumptions!C9,(18-1)*12+1,18*12,0) -> 30381.879 | F22: =-CUMPRINC(Assumptions!C17,Assumptions!C18,Assumptions!C9,(18-1)*12+1,18*12,0) -> 27174.971 | G22: =C22-F22 -> 491510.29
B23: 19 | C23: =G22 -> 491510.29 | D23: =Assumptions!C20 -> 57556.85 | E23: =-CUMIPMT(Assumptions!C17,Assumptions!C18,Assumptions!C9,(19-1)*12+1,19*12,0) -> 28705.786 | F23: =-CUMPRINC(Assumptions!C17,Assumptions!C18,Assumptions!C9,(19-1)*12+1,19*12,0) -> 28851.064 | G23: =C23-F23 -> 462659.22
B24: 20 | C24: =G23 -> 462659.22 | D24: =Assumptions!C20 -> 57556.85 | E24: =-CUMIPMT(Assumptions!C17,Assumptions!C18,Assumptions!C9,(20-1)*12+1,20*12,0) -> 26926.316 | F24: =-CUMPRINC(Assumptions!C17,Assumptions!C18,Assumptions!C9,(20-1)*12+1,20*12,0) -> 30630.535 | G24: =C24-F24 -> 432028.69
B25: 21 | C25: =G24 -> 432028.69 | D25: =Assumptions!C20 -> 57556.85 | E25: =-CUMIPMT(Assumptions!C17,Assumptions!C18,Assumptions!C9,(21-1)*12+1,21*12,0) -> 25037.091 | F25: =-CUMPRINC(Assumptions!C17,Assumptions!C18,Assumptions!C9,(21-1)*12+1,21*12,0) -> 32519.759 | G25: =C25-F25 -> 399508.93
B26: 22 | C26: =G25 -> 399508.93 | D26: =Assumptions!C20 -> 57556.85 | E26: =-CUMIPMT(Assumptions!C17,Assumptions!C18,Assumptions!C9,(22-1)*12+1,22*12,0) -> 23031.344 | F26: =-CUMPRINC(Assumptions!C17,Assumptions!C18,Assumptions!C9,(22-1)*12+1,22*12,0) -> 34525.507 | G26: =C26-F26 -> 364983.42
B27: 23 | C27: =G26 -> 364983.42 | D27: =Assumptions!C20 -> 57556.85 | E27: =-CUMIPMT(Assumptions!C17,Assumptions!C18,Assumptions!C9,(23-1)*12+1,23*12,0) -> 20901.886 | F27: =-CUMPRINC(Assumptions!C17,Assumptions!C18,Assumptions!C9,(23-1)*12+1,23*12,0) -> 36654.964 | G27: =C27-F27 -> 328328.46
B28: 24 | C28: =G27 -> 328328.46 | D28: =Assumptions!C20 -> 57556.85 | E28: =-CUMIPMT(Assumptions!C17,Assumptions!C18,Assumptions!C9,(24-1)*12+1,24*12,0) -> 18641.088 | F28: =-CUMPRINC(Assumptions!C17,Assumptions!C18,Assumptions!C9,(24-1)*12+1,24*12,0) -> 38915.762 | G28: =C28-F28 -> 289412.7
B29: 25 | C29: =G28 -> 289412.7 | D29: =Assumptions!C20 -> 57556.85 | E29: =-CUMIPMT(Assumptions!C17,Assumptions!C18,Assumptions!C9,(25-1)*12+1,25*12,0) -> 16240.849 | F29: =-CUMPRINC(Assumptions!C17,Assumptions!C18,Assumptions!C9,(25-1)*12+1,25*12,0) -> 41316.001 | G29: =C29-F29 -> 248096.7
B30: 26 | C30: =G29 -> 248096.7 | D30: =Assumptions!C20 -> 57556.85 | E30: =-CUMIPMT(Assumptions!C17,Assumptions!C18,Assumptions!C9,(26-1)*12+1,26*12,0) -> 13692.569 | F30: =-CUMPRINC(Assumptions!C17,Assumptions!C18,Assumptions!C9,(26-1)*12+1,26*12,0) -> 43864.282 | G30: =C30-F30 -> 204232.42
B31: 27 | C31: =G30 -> 204232.42 | D31: =Assumptions!C20 -> 57556.85 | E31: =-CUMIPMT(Assumptions!C17,Assumptions!C18,Assumptions!C9,(27-1)*12+1,27*12,0) -> 10987.116 | F31: =-CUMPRINC(Assumptions!C17,Assumptions!C18,Assumptions!C9,(27-1)*12+1,27*12,0) -> 46569.735 | G31: =C31-F31 -> 157662.68
B32: 28 | C32: =G31 -> 157662.68 | D32: =Assumptions!C20 -> 57556.85 | E32: =-CUMIPMT(Assumptions!C17,Assumptions!C18,Assumptions!C9,(28-1)*12+1,28*12,0) -> 8114.7964 | F32: =-CUMPRINC(Assumptions!C17,Assumptions!C18,Assumptions!C9,(28-1)*12+1,28*12,0) -> 49442.054 | G32: =C32-F32 -> 108220.63
B33: 29 | C33: =G32 -> 108220.63 | D33: =Assumptions!C20 -> 57556.85 | E33: =-CUMIPMT(Assumptions!C17,Assumptions!C18,Assumptions!C9,(29-1)*12+1,29*12,0) -> 5065.3187 | F33: =-CUMPRINC(Assumptions!C17,Assumptions!C18,Assumptions!C9,(29-1)*12+1,29*12,0) -> 52491.532 | G33: =C33-F33 -> 55729.095
B34: 30 | C34: =G33 -> 55729.095 | D34: =Assumptions!C20 -> 57556.85 | E34: =-CUMIPMT(Assumptions!C17,Assumptions!C18,Assumptions!C9,(30-1)*12+1,30*12,0) -> 1827.7558 | F34: =-CUMPRINC(Assumptions!C17,Assumptions!C18,Assumptions!C9,(30-1)*12+1,30*12,0) -> 55729.095 | G34: =C34-F34 -> 1.8735591e-08
B35: TOTAL | D35: =SUM(D5:D34) -> 1726705.5 | E35: =SUM(E5:E34) -> 926705.51 | F35: =SUM(F5:F34) -> 800000

Sheet Scenario Comparison
B2: Scenario Comparison — Base / Bull / Bear
B4: Metric | C4: Bear Case (0.5%) | D4: Base Case (2.5%) | E4: Bull Case (4.0%)
B5: Annual Appreciation Rate | C5: =Assumptions!C31 -> 0.005 | D5: =Assumptions!C29 -> 0.025 | E5: =Assumptions!C30 -> 0.04
B6: Year 10 Property Value | C6: =Assumptions!C6*(1+Assumptions!C31)^10 -> 1051140.1 | D6: =Assumptions!C6*(1+Assumptions!C29)^10 -> 1280084.5 | E6: =Assumptions!C6*(1+Assumptions!C30)^10 -> 1480244.3
B7: Total Appreciation ($) | C7: =C6-Assumptions!C6 -> 51140.132 | D7: =D6-Assumptions!C6 -> 280084.54 | E7: =E6-Assumptions!C6 -> 480244.28
B8: Mortgage Balance (Year 10) | C8: =Amortization!G14 -> 669485.8 | D8: =Amortization!G14 -> 669485.8 | E8: =Amortization!G14 -> 669485.8
B9: Net Equity at Disposition | C9: =C6-C8 -> 381654.33 | D9: =D6-D8 -> 610598.74 | E9: =E6-E8 -> 810758.49
B10: Disposition Costs | C10: =-C6*Assumptions!C35 -> -52557.007 | D10: =-D6*Assumptions!C35 -> -64004.227 | E10: =-E6*Assumptions!C35 -> -74012.214
B11: Net Sale Proceeds | C11: =C6+C10-C8 -> 329097.33 | D11: =D6+D10-D8 -> 546594.52 | E11: =E6+E10-E8 -> 736746.27
B12: Cumulative Cash Flow (Ops) | C12: ='10-Year Model'!M26 -> -437578.93 | D12: ='10-Year Model'!M26 -> -437578.93 | E12: ='10-Year Model'!M26 -> -437578.93
B13: Total Profit | C13: =C11+C12+Assumptions!C12 -> 116518.39 | D13: =D11+D12+Assumptions!C12 -> 334015.58 | E13: =E11+E12+Assumptions!C12 -> 524167.34
B14: Equity Multiple | C14: =(C11+'10-Year Model'!M26+SUM('10-Year Model'!D25:L25))/Assumptions!C12 -> -1.3509638 | D14: =(D11+'10-Year Model'!M26+SUM('10-Year Model'!D25:L25))/Assumptions!C12 -> -0.38430961 | E14: =(E11+'10-Year Model'!M26+SUM('10-Year Model'!D25:L25))/Assumptions!C12 -> 0.4608093

Sheet Sensitivity Analysis
B2: Sensitivity Analysis — IRR Under Varying Assumptions
B4: Total Equity at Year 10: Interest Rate (rows) vs. Annual Appreciation (columns)
B5: Interest Rate ▼ / Appr ▶ | C5: -0.5% | D5: 0.0% | E5: 0.5% | F5: 1.0% | G5: 2.0% | H5: 3.0% | I5: 4.0% | J5: 5.0%
B6: 0.05 | C6: =Assumptions!C6*(1+-0.005)^10-FV(0.05/12,120,PMT(0.05/12,360,Assumptions!C9),-Assumptions!C9) -> -1033368.5 | D6: =Assumptions!C6*(1+0)^10-FV(0.05/12,120,PMT(0.05/12,360,Assumptions!C9),-Assumptions!C9) -> -984478.68 | E6: =Assumptions!C6*(1+0.005)^10-FV(0.05/12,120,PMT(0.05/12,360,Assumptions!C9),-Assumptions!C9) -> -933338.55 | F6: =Assumptions!C6*(1+0.01)^10-FV(0.05/12,120,PMT(0.05/12,360,Assumptions!C9),-Assumptions!C9) -> -879856.55 | G6: =Assumptions!C6*(1+0.02)^10-FV(0.05/12,120,PMT(0.05/12,360,Assumptions!C9),-Assumptions!C9) -> -765484.26 | H6: =Assumptions!C6*(1+0.03)^10-FV(0.05/12,120,PMT(0.05/12,360,Assumptions!C9),-Assumptions!C9) -> -640562.3 | I6: =Assumptions!C6*(1+0.04)^10-FV(0.05/12,120,PMT(0.05/12,360,Assumptions!C9),-Assumptions!C9) -> -504234.4 | J6: =Assumptions!C6*(1+0.05)^10-FV(0.05/12,120,PMT(0.05/12,360,Assumptions!C9),-Assumptions!C9) -> -355584.05
B7: 0.055 | C7: =Assumptions!C6*(1+-0.005)^10-FV(0.055/12,120,PMT(0.055/12,360,Assumptions!C9),-Assumptions!C9) -> -1158284.2 | D7: =Assumptions!C6*(1+0)^10-FV(0.055/12,120,PMT(0.055/12,360,Assumptions!C9),-Assumptions!C9) -> -1109394.3 | E7: =Assumptions!C6*(1+0.005)^10-FV(0.055/12,120,PMT(0.055/12,360,Assumptions!C9),-Assumptions!C9) -> -1058254.2 | F7: =Assumptions!C6*(1+0.01)^10-FV(0.055/12,120,PMT(0.055/12,360,Assumptions!C9),-Assumptions!C9) -> -1004772.2 | G7: =Assumptions!C6*(1+0.02)^10-FV(0.055/12,120,PMT(0.055/12,360,Assumptions!C9),-Assumptions!C9) -> -890399.92 | H7: =Assumptions!C6*(1+0.03)^10-FV(0.055/12,120,PMT(0.055/12,360,Assumptions!C9),-Assumptions!C9) -> -765477.96 | I7: =Assumptions!C6*(1+0.04)^10-FV(0.055/12,120,PMT(0.055/12,360,Assumptions!C9),-Assumptions!C9) -> -629150.05 | J7: =Assumptions!C6*(1+0.05)^10-FV(0.055/12,120,PMT(0.055/12,360,Assumptions!C9),-Assumptions!C9) -> -480499.71
B8: 0.06 | C8: =Assumptions!C6*(1+-0.005)^10-FV(0.06/12,120,PMT(0.06/12,360,Assumptions!C9),-Assumptions!C9) -> -1290438.8 | D8: =Assumptions!C6*(1+0)^10-FV(0.06/12,120,PMT(0.06/12,360,Assumptions!C9),-Assumptions!C9) -> -1241549 | E8: =Assumptions!C6*(1+0.005)^10-FV(0.06/12,120,PMT(0.06/12,360,Assumptions!C9),-Assumptions!C9) -> -1190408.8 | F8: =Assumptions!C6*(1+0.01)^10-FV(0.06/12,120,PMT(0.06/12,360,Assumptions!C9),-Assumptions!C9) -> -1136926.8 | G8: =Assumptions!C6*(1+0.02)^10-FV(0.06/12,120,PMT(0.06/12,360,Assumptions!C9),-Assumptions!C9) -> -1022554.6 | H8: =Assumptions!C6*(1+0.03)^10-FV(0.06/12,120,PMT(0.06/12,360,Assumptions!C9),-Assumptions!C9) -> -897632.6 | I8: =Assumptions!C6*(1+0.04)^10-FV(0.06/12,120,PMT(0.06/12,360,Assumptions!C9),-Assumptions!C9) -> -761304.69 | J8: =Assumptions!C6*(1+0.05)^10-FV(0.06/12,120,PMT(0.06/12,360,Assumptions!C9),-Assumptions!C9) -> -612654.35
B9: 0.065 | C9: =Assumptions!C6*(1+-0.005)^10-FV(0.065/12,120,PMT(0.065/12,360,Assumptions!C9),-Assumptions!C9) -> -1430174.9 | D9: =Assumptions!C6*(1+0)^10-FV(0.065/12,120,PMT(0.065/12,360,Assumptions!C9),-Assumptions!C9) -> -1381285 | E9: =Assumptions!C6*(1+0.005)^10-FV(0.065/12,120,PMT(0.065/12,360,Assumptions!C9),-Assumptions!C9) -> -1330144.9 | F9: =Assumptions!C6*(1+0.01)^10-FV(0.065/12,120,PMT(0.065/12,360,Assumptions!C9),-Assumptions!C9) -> -1276662.9 | G9: =Assumptions!C6*(1+0.02)^10-FV(0.065/12,120,PMT(0.065/12,360,Assumptions!C9),-Assumptions!C9) -> -1162290.6 | H9: =Assumptions!C6*(1+0.03)^10-FV(0.065/12,120,PMT(0.065/12,360,Assumptions!C9),-Assumptions!C9) -> -1037368.6 | I9: =Assumptions!C6*(1+0.04)^10-FV(0.065/12,120,PMT(0.065/12,360,Assumptions!C9),-Assumptions!C9) -> -901040.71 | J9: =Assumptions!C6*(1+0.05)^10-FV(0.065/12,120,PMT(0.065/12,360,Assumptions!C9),-Assumptions!C9) -> -752390.37
B10: 0.07 | C10: =Assumptions!C6*(1+-0.005)^10-FV(0.07/12,120,PMT(0.07/12,360,Assumptions!C9),-Assumptions!C9) -> -1577849 | D10: =Assumptions!C6*(1+0)^10-FV(0.07/12,120,PMT(0.07/12,360,Assumptions!C9),-Assumptions!C9) -> -1528959.1 | E10: =Assumptions!C6*(1+0.005)^10-FV(0.07/12,120,PMT(0.07/12,360,Assumptions!C9),-Assumptions!C9) -> -1477819 | F10: =Assumptions!C6*(1+0.01)^10-FV(0.07/12,120,PMT(0.07/12,360,Assumptions!C9),-Assumptions!C9) -> -1424337 | G10: =Assumptions!C6*(1+0.02)^10-FV(0.07/12,120,PMT(0.07/12,360,Assumptions!C9),-Assumptions!C9) -> -1309964.7 | H10: =Assumptions!C6*(1+0.03)^10-FV(0.07/12,120,PMT(0.07/12,360,Assumptions!C9),-Assumptions!C9) -> -1185042.8 | I10: =Assumptions!C6*(1+0.04)^10-FV(0.07/12,120,PMT(0.07/12,360,Assumptions!C9),-Assumptions!C9) -> -1048714.9 | J10: =Assumptions!C6*(1+0.05)^10-FV(0.07/12,120,PMT(0.07/12,360,Assumptions!C9),-Assumptions!C9) -> -900064.51
B13: Year 1 Annual Cash Flow: Interest Rate (rows) vs. Annual Appreciation (columns)
B14: Interest Rate ▼ / Appr ▶ | C14: -0.5% | D14: 0.0% | E14: 0.5% | F14: 1.0% | G14: 2.0% | H14: 3.0% | I14: 4.0% | J14: 5.0%
B15: 0.05 | C15: =Assumptions!C23*12*(1-Assumptions!C25)*(1-Assumptions!C26)--PMT(0.05/12,Assumptions!C18,Assumptions!C9)*12 -> -19134.876 | D15: =Assumptions!C23*12*(1-Assumptions!C25)*(1-Assumptions!C26)--PMT(0.05/12,Assumptions!C18,Assumptions!C9)*12 -> -19134.876 | E15: =Assumptions!C23*12*(1-Assumptions!C25)*(1-Assumptions!C26)--PMT(0.05/12,Assumptions!C18,Assumptions!C9)*12 -> -19134.876 | F15: =Assumptions!C23*12*(1-Assumptions!C25)*(1-Assumptions!C26)--PMT(0.05/12,Assumptions!C18,Assumptions!C9)*12 -> -19134.876 | G15: =Assumptions!C23*12*(1-Assumptions!C25)*(1-Assumptions!C26)--PMT(0.05/12,Assumptions!C18,Assumptions!C9)*12 -> -19134.876 | H15: =Assumptions!C23*12*(1-Assumptions!C25)*(1-Assumptions!C26)--PMT(0.05/12,Assumptions!C18,Assumptions!C9)*12 -> -19134.876 | I15: =Assumptions!C23*12*(1-Assumptions!C25)*(1-Assumptions!C26)--PMT(0.05/12,Assumptions!C18,Assumptions!C9)*12 -> -19134.876 | J15: =Assumptions!C23*12*(1-Assumptions!C25)*(1-Assumptions!C26)--PMT(0.05/12,Assumptions!C18,Assumptions!C9)*12 -> -19134.876
B16: 0.055 | C16: =Assumptions!C23*12*(1-Assumptions!C25)*(1-Assumptions!C26)--PMT(0.055/12,Assumptions!C18,Assumptions!C9)*12 -> -22107.744 | D16: =Assumptions!C23*12*(1-Assumptions!C25)*(1-Assumptions!C26)--PMT(0.055/12,Assumptions!C18,Assumptions!C9)*12 -> -22107.744 | E16: =Assumptions!C23*12*(1-Assumptions!C25)*(1-Assumptions!C26)--PMT(0.055/12,Assumptions!C18,Assumptions!C9)*12 -> -22107.744 | F16: =Assumptions!C23*12*(1-Assumptions!C25)*(1-Assumptions!C26)--PMT(0.055/12,Assumptions!C18,Assumptions!C9)*12 -> -22107.744 | G16: =Assumptions!C23*12*(1-Assumptions!C25)*(1-Assumptions!C26)--PMT(0.055/12,Assumptions!C18,Assumptions!C9)*12 -> -22107.744 | H16: =Assumptions!C23*12*(1-Assumptions!C25)*(1-Assumptions!C26)--PMT(0.055/12,Assumptions!C18,Assumptions!C9)*12 -> -22107.744 | I16: =Assumptions!C23*12*(1-Assumptions!C25)*(1-Assumptions!C26)--PMT(0.055/12,Assumptions!C18,Assumptions!C9)*12 -> -22107.744 | J16: =Assumptions!C23*12*(1-Assumptions!C25)*(1-Assumptions!C26)--PMT(0.055/12,Assumptions!C18,Assumptions!C9)*12 -> -22107.744
B17: 0.06 | C17: =Assumptions!C23*12*(1-Assumptions!C25)*(1-Assumptions!C26)--PMT(0.06/12,Assumptions!C18,Assumptions!C9)*12 -> -25156.85 | D17: =Assumptions!C23*12*(1-Assumptions!C25)*(1-Assumptions!C26)--PMT(0.06/12,Assumptions!C18,Assumptions!C9)*12 -> -25156.85 | E17: =Assumptions!C23*12*(1-Assumptions!C25)*(1-Assumptions!C26)--PMT(0.06/12,Assumptions!C18,Assumptions!C9)*12 -> -25156.85 | F17: =Assumptions!C23*12*(1-Assumptions!C25)*(1-Assumptions!C26)--PMT(0.06/12,Assumptions!C18,Assumptions!C9)*12 -> -25156.85 | G17: =Assumptions!C23*12*(1-Assumptions!C25)*(1-Assumptions!C26)--PMT(0.06/12,Assumptions!C18,Assumptions!C9)*12 -> -25156.85 | H17: =Assumptions!C23*12*(1-Assumptions!C25)*(1-Assumptions!C26)--PMT(0.06/12,Assumptions!C18,Assumptions!C9)*12 -> -25156.85 | I17: =Assumptions!C23*12*(1-Assumptions!C25)*(1-Assumptions!C26)--PMT(0.06/12,Assumptions!C18,Assumptions!C9)*12 -> -25156.85 | J17: =Assumptions!C23*12*(1-Assumptions!C25)*(1-Assumptions!C26)--PMT(0.06/12,Assumptions!C18,Assumptions!C9)*12 -> -25156.85
B18: 0.065 | C18: =Assumptions!C23*12*(1-Assumptions!C25)*(1-Assumptions!C26)--PMT(0.065/12,Assumptions!C18,Assumptions!C9)*12 -> -28278.53 | D18: =Assumptions!C23*12*(1-Assumptions!C25)*(1-Assumptions!C26)--PMT(0.065/12,Assumptions!C18,Assumptions!C9)*12 -> -28278.53 | E18: =Assumptions!C23*12*(1-Assumptions!C25)*(1-Assumptions!C26)--PMT(0.065/12,Assumptions!C18,Assumptions!C9)*12 -> -28278.53 | F18: =Assumptions!C23*12*(1-Assumptions!C25)*(1-Assumptions!C26)--PMT(0.065/12,Assumptions!C18,Assumptions!C9)*12 -> -28278.53 | G18: =Assumptions!C23*12*(1-Assumptions!C25)*(1-Assumptions!C26)--PMT(0.065/12,Assumptions!C18,Assumptions!C9)*12 -> -28278.53 | H18: =Assumptions!C23*12*(1-Assumptions!C25)*(1-Assumptions!C26)--PMT(0.065/12,Assumptions!C18,Assumptions!C9)*12 -> -28278.53 | I18: =Assumptions!C23*12*(1-Assumptions!C25)*(1-Assumptions!C26)--PMT(0.065/12,Assumptions!C18,Assumptions!C9)*12 -> -28278.53 | J18: =Assumptions!C23*12*(1-Assumptions!C25)*(1-Assumptions!C26)--PMT(0.065/12,Assumptions!C18,Assumptions!C9)*12 -> -28278.53
B19: 0.07 | C19: =Assumptions!C23*12*(1-Assumptions!C25)*(1-Assumptions!C26)--PMT(0.07/12,Assumptions!C18,Assumptions!C9)*12 -> -31469.04 | D19: =Assumptions!C23*12*(1-Assumptions!C25)*(1-Assumptions!C26)--PMT(0.07/12,Assumptions!C18,Assumptions!C9)*12 -> -31469.04 | E19: =Assumptions!C23*12*(1-Assumptions!C25)*(1-Assumptions!C26)--PMT(0.07/12,Assumptions!C18,Assumptions!C9)*12 -> -31469.04 | F19: =Assumptions!C23*12*(1-Assumptions!C25)*(1-Assumptions!C26)--PMT(0.07/12,Assumptions!C18,Assumptions!C9)*12 -> -31469.04 | G19: =Assumptions!C23*12*(1-Assumptions!C25)*(1-Assumptions!C26)--PMT(0.07/12,Assumptions!C18,Assumptions!C9)*12 -> -31469.04 | H19: =Assumptions!C23*12*(1-Assumptions!C25)*(1-Assumptions!C26)--PMT(0.07/12,Assumptions!C18,Assumptions!C9)*12 -> -31469.04 | I19: =Assumptions!C23*12*(1-Assumptions!C25)*(1-Assumptions!C26)--PMT(0.07/12,Assumptions!C18,Assumptions!C9)*12 -> -31469.04 | J19: =Assumptions!C23*12*(1-Assumptions!C25)*(1-Assumptions!C26)--PMT(0.07/12,Assumptions!C18,Assumptions!C9)*12 -> -31469.04
B22: Net Sale Proceeds at Year 10: Interest Rate (rows) vs. Annual Appreciation (columns)
B23: Interest Rate ▼ / Appr ▶ | C23: -0.5% | D23: 0.0% | E23: 0.5% | F23: 1.0% | G23: 2.0% | H23: 3.0% | I23: 4.0% | J23: 5.0%
B24: 0.05 | C24: =Assumptions!C6*(1+-0.005)^10*(1-Assumptions!C35)-FV(0.05/12,120,PMT(0.05/12,360,Assumptions!C9),-Assumptions!C9) -> -1080924.1 | D24: =Assumptions!C6*(1+0)^10*(1-Assumptions!C35)-FV(0.05/12,120,PMT(0.05/12,360,Assumptions!C9),-Assumptions!C9) -> -1034478.7 | E24: =Assumptions!C6*(1+0.005)^10*(1-Assumptions!C35)-FV(0.05/12,120,PMT(0.05/12,360,Assumptions!C9),-Assumptions!C9) -> -985895.55 | F24: =Assumptions!C6*(1+0.01)^10*(1-Assumptions!C35)-FV(0.05/12,120,PMT(0.05/12,360,Assumptions!C9),-Assumptions!C9) -> -935087.66 | G24: =Assumptions!C6*(1+0.02)^10*(1-Assumptions!C35)-FV(0.05/12,120,PMT(0.05/12,360,Assumptions!C9),-Assumptions!C9) -> -826433.98 | H24: =Assumptions!C6*(1+0.03)^10*(1-Assumptions!C35)-FV(0.05/12,120,PMT(0.05/12,360,Assumptions!C9),-Assumptions!C9) -> -707758.12 | I24: =Assumptions!C6*(1+0.04)^10*(1-Assumptions!C35)-FV(0.05/12,120,PMT(0.05/12,360,Assumptions!C9),-Assumptions!C9) -> -578246.61 | J24: =Assumptions!C6*(1+0.05)^10*(1-Assumptions!C35)-FV(0.05/12,120,PMT(0.05/12,360,Assumptions!C9),-Assumptions!C9) -> -437028.78
B25: 0.055 | C25: =Assumptions!C6*(1+-0.005)^10*(1-Assumptions!C35)-FV(0.055/12,120,PMT(0.055/12,360,Assumptions!C9),-Assumptions!C9) -> -1205839.7 | D25: =Assumptions!C6*(1+0)^10*(1-Assumptions!C35)-FV(0.055/12,120,PMT(0.055/12,360,Assumptions!C9),-Assumptions!C9) -> -1159394.3 | E25: =Assumptions!C6*(1+0.005)^10*(1-Assumptions!C35)-FV(0.055/12,120,PMT(0.055/12,360,Assumptions!C9),-Assumptions!C9) -> -1110811.2 | F25: =Assumptions!C6*(1+0.01)^10*(1-Assumptions!C35)-FV(0.055/12,120,PMT(0.055/12,360,Assumptions!C9),-Assumptions!C9) -> -1060003.3 | G25: =Assumptions!C6*(1+0.02)^10*(1-Assumptions!C35)-FV(0.055/12,120,PMT(0.055/12,360,Assumptions!C9),-Assumptions!C9) -> -951349.64 | H25: =Assumptions!C6*(1+0.03)^10*(1-Assumptions!C35)-FV(0.055/12,120,PMT(0.055/12,360,Assumptions!C9),-Assumptions!C9) -> -832673.78 | I25: =Assumptions!C6*(1+0.04)^10*(1-Assumptions!C35)-FV(0.055/12,120,PMT(0.055/12,360,Assumptions!C9),-Assumptions!C9) -> -703162.27 | J25: =Assumptions!C6*(1+0.05)^10*(1-Assumptions!C35)-FV(0.055/12,120,PMT(0.055/12,360,Assumptions!C9),-Assumptions!C9) -> -561944.44
B26: 0.06 | C26: =Assumptions!C6*(1+-0.005)^10*(1-Assumptions!C35)-FV(0.06/12,120,PMT(0.06/12,360,Assumptions!C9),-Assumptions!C9) -> -1337994.4 | D26: =Assumptions!C6*(1+0)^10*(1-Assumptions!C35)-FV(0.06/12,120,PMT(0.06/12,360,Assumptions!C9),-Assumptions!C9) -> -1291549 | E26: =Assumptions!C6*(1+0.005)^10*(1-Assumptions!C35)-FV(0.06/12,120,PMT(0.06/12,360,Assumptions!C9),-Assumptions!C9) -> -1242965.8 | F26: =Assumptions!C6*(1+0.01)^10*(1-Assumptions!C35)-FV(0.06/12,120,PMT(0.06/12,360,Assumptions!C9),-Assumptions!C9) -> -1192158 | G26: =Assumptions!C6*(1+0.02)^10*(1-Assumptions!C35)-FV(0.06/12,120,PMT(0.06/12,360,Assumptions!C9),-Assumptions!C9) -> -1083504.3 | H26: =Assumptions!C6*(1+0.03)^10*(1-Assumptions!C35)-FV(0.06/12,120,PMT(0.06/12,360,Assumptions!C9),-Assumptions!C9) -> -964828.41 | I26: =Assumptions!C6*(1+0.04)^10*(1-Assumptions!C35)-FV(0.06/12,120,PMT(0.06/12,360,Assumptions!C9),-Assumptions!C9) -> -835316.9 | J26: =Assumptions!C6*(1+0.05)^10*(1-Assumptions!C35)-FV(0.06/12,120,PMT(0.06/12,360,Assumptions!C9),-Assumptions!C9) -> -694099.08
B27: 0.065 | C27: =Assumptions!C6*(1+-0.005)^10*(1-Assumptions!C35)-FV(0.065/12,120,PMT(0.065/12,360,Assumptions!C9),-Assumptions!C9) -> -1477730.4 | D27: =Assumptions!C6*(1+0)^10*(1-Assumptions!C35)-FV(0.065/12,120,PMT(0.065/12,360,Assumptions!C9),-Assumptions!C9) -> -1431285 | E27: =Assumptions!C6*(1+0.005)^10*(1-Assumptions!C35)-FV(0.065/12,120,PMT(0.065/12,360,Assumptions!C9),-Assumptions!C9) -> -1382701.9 | F27: =Assumptions!C6*(1+0.01)^10*(1-Assumptions!C35)-FV(0.065/12,120,PMT(0.065/12,360,Assumptions!C9),-Assumptions!C9) -> -1331894 | G27: =Assumptions!C6*(1+0.02)^10*(1-Assumptions!C35)-FV(0.065/12,120,PMT(0.065/12,360,Assumptions!C9),-Assumptions!C9) -> -1223240.3 | H27: =Assumptions!C6*(1+0.03)^10*(1-Assumptions!C35)-FV(0.065/12,120,PMT(0.065/12,360,Assumptions!C9),-Assumptions!C9) -> -1104564.4 | I27: =Assumptions!C6*(1+0.04)^10*(1-Assumptions!C35)-FV(0.065/12,120,PMT(0.065/12,360,Assumptions!C9),-Assumptions!C9) -> -975052.92 | J27: =Assumptions!C6*(1+0.05)^10*(1-Assumptions!C35)-FV(0.065/12,120,PMT(0.065/12,360,Assumptions!C9),-Assumptions!C9) -> -833835.1
B28: 0.07 | C28: =Assumptions!C6*(1+-0.005)^10*(1-Assumptions!C35)-FV(0.07/12,120,PMT(0.07/12,360,Assumptions!C9),-Assumptions!C9) -> -1625404.5 | D28: =Assumptions!C6*(1+0)^10*(1-Assumptions!C35)-FV(0.07/12,120,PMT(0.07/12,360,Assumptions!C9),-Assumptions!C9) -> -1578959.1 | E28: =Assumptions!C6*(1+0.005)^10*(1-Assumptions!C35)-FV(0.07/12,120,PMT(0.07/12,360,Assumptions!C9),-Assumptions!C9) -> -1530376 | F28: =Assumptions!C6*(1+0.01)^10*(1-Assumptions!C35)-FV(0.07/12,120,PMT(0.07/12,360,Assumptions!C9),-Assumptions!C9) -> -1479568.1 | G28: =Assumptions!C6*(1+0.02)^10*(1-Assumptions!C35)-FV(0.07/12,120,PMT(0.07/12,360,Assumptions!C9),-Assumptions!C9) -> -1370914.4 | H28: =Assumptions!C6*(1+0.03)^10*(1-Assumptions!C35)-FV(0.07/12,120,PMT(0.07/12,360,Assumptions!C9),-Assumptions!C9) -> -1252238.6 | I28: =Assumptions!C6*(1+0.04)^10*(1-Assumptions!C35)-FV(0.07/12,120,PMT(0.07/12,360,Assumptions!C9),-Assumptions!C9) -> -1122727.1 | J28: =Assumptions!C6*(1+0.05)^10*(1-Assumptions!C35)-FV(0.07/12,120,PMT(0.07/12,360,Assumptions!C9),-Assumptions!C9) -> -981509.24

Sheet Dashboard
B2: Executive Dashboard — Toronto Condo Investment
B4: KEY INVESTMENT METRICS | E4: RISK INDICATORS
B5: Purchase Price | C5: =Assumptions!C6 -> 1000000 | E5: Debt Service Coverage Ratio (Yr 1) | F5: ='10-Year Model'!D17/(-'10-Year Model'!D20) -> 0.5629217
B6: Total Cash Invested | C6: =Assumptions!C12 -> 225000 | E6: Loan-to-Value Ratio | F6: =1-Assumptions!C7 -> 0.8
B7: Monthly Mortgage Payment | C7: =Assumptions!C19 -> 4796.4042 | E7: Break-Even Occupancy | F7: =(-'10-Year Model'!D20+'10-Year Model'!D16)/(Assumptions!C23*12) -> 0.97410105
B8: Year 1 NOI | C8: ='10-Year Model'!D17 -> 32400 | E8: Monthly Cash Shortfall (Yr 1) | F8: ='10-Year Model'!D25/12 -> -2096.4042
B9: Year 1 Cash Flow | C9: ='10-Year Model'!D25 -> -25156.85 | E9: Years to Positive Cash Flow | F9: See Model
B10: Year 1 Cash-on-Cash Return | C10: ='10-Year Model'!C45 -> -0.11180822 | E10: Vacancy Buffer Before Loss | F10: =('10-Year Model'!D17)/(-'10-Year Model'!D20+'10-Year Model'!D16+'10-Year Model'!D17) -> 0.40931391
B11: Year 1 Cap Rate | C11: ='10-Year Model'!C46 -> 0.0324
B12: Year 10 Property Value (Base) | C12: ='10-Year Model'!M7 -> 1280084.5 | E12: MARKET CONTEXT (Q4 2025)
B13: Year 10 Net Equity | C13: ='10-Year Model'!M32 -> 610598.74 | E13: GTA Avg Condo Price (TRREB) | F13: $652,945
B14: Net Sale Proceeds | C14: ='10-Year Model'!M38 -> 546594.52 | E14: City of Toronto Avg Price | F14: $690,607
B15: 10-Year IRR (Leveraged) | C15: ='10-Year Model'!C42 -> 0.029521862 | E15: YoY Price Change (GTA) | F15: -5.1%
B16: Equity Multiple | C16: ='10-Year Model'!C44 -> 1.4845137 | E16: Avg Rent (All Condos) | F16: $2,592/month
B17: Total Profit | C17: ='10-Year Model'!C43 -> 334015.58 | E17: Rent YoY Change | F17: -6.0%
E18: Avg Days on Market | F18: 42 days
E19: Sale-to-List Price Ratio | F19: 97%
E20: BoC Policy Rate | F20: 2.25%
E21: Condo Completions 2025 | F21: 31,422 units (record)
E22: Condo Starts 2025 | F22: Lowest since 1998

Sheet Charts
B2: Chart Data — Equity Growth & Cash Flow Over Time
B4: Year | C4: Total Equity | D4: Cumulative Cash Flow | E4: Property Value | F4: Mortgage Balance
B5: 0 | C5: ='10-Year Model'!C32 -> 200000 | D5: ='10-Year Model'!C26 -> -225000 | E5: ='10-Year Model'!C7 -> 1000000 | F5: =IF(0=0,Assumptions!C9,'10-Year Model'!C29) -> 800000
B6: 1 | C6: ='10-Year Model'!D32 -> 234824.09 | D6: ='10-Year Model'!D26 -> -250156.85 | E6: ='10-Year Model'!D7 -> 1025000 | F6: =IF(1=0,Assumptions!C9,'10-Year Model'!D29) -> 790175.91
B7: 2 | C7: ='10-Year Model'!E32 -> 270879.12 | D7: ='10-Year Model'!E26 -> -274503.7 | E7: ='10-Year Model'!E7 -> 1050625 | F7: =IF(2=0,Assumptions!C9,'10-Year Model'!E29) -> 779745.88
B8: 3 | C8: ='10-Year Model'!F32 -> 308218.06 | D8: ='10-Year Model'!F26 -> -298020.3 | E8: ='10-Year Model'!F7 -> 1076890.6 | F8: =IF(3=0,Assumptions!C9,'10-Year Model'!F29) -> 768672.56
B9: 4 | C9: ='10-Year Model'!G32 -> 346896.63 | D9: ='10-Year Model'!G26 -> -320685.9 | E9: ='10-Year Model'!G7 -> 1103812.9 | F9: =IF(4=0,Assumptions!C9,'10-Year Model'!G29) -> 756916.26
B10: 5 | C10: ='10-Year Model'!H32 -> 386973.36 | D10: ='10-Year Model'!H26 -> -342479.21 | E10: ='10-Year Model'!H7 -> 1131408.2 | F10: =IF(5=0,Assumptions!C9,'10-Year Model'!H29) -> 744434.85
B11: 6 | C11: ='10-Year Model'!I32 -> 428509.79 | D11: ='10-Year Model'!I26 -> -363378.43 | E11: ='10-Year Model'!I7 -> 1159693.4 | F11: =IF(6=0,Assumptions!C9,'10-Year Model'!I29) -> 731183.62
B12: 7 | C12: ='10-Year Model'!J32 -> 471570.67 | D12: ='10-Year Model'!J26 -> -383361.22 | E12: ='10-Year Model'!J7 -> 1188685.8 | F12: =IF(7=0,Assumptions!C9,'10-Year Model'!J29) -> 717115.09
B13: 8 | C13: ='10-Year Model'!K32 -> 516224.06 | D13: ='10-Year Model'!K26 -> -402404.65 | E13: ='10-Year Model'!K7 -> 1218402.9 | F13: =IF(8=0,Assumptions!C9,'10-Year Model'!K29) -> 702178.83
B14: 9 | C14: ='10-Year Model'!L32 -> 562541.63 | D14: ='10-Year Model'!L26 -> -420485.24 | E14: ='10-Year Model'!L7 -> 1248863 | F14: =IF(9=0,Assumptions!C9,'10-Year Model'!L29) -> 686321.34
B15: 10 | C15: ='10-Year Model'!M32 -> 610598.74 | D15: ='10-Year Model'!M26 -> -437578.93 | E15: ='10-Year Model'!M7 -> 1280084.5 | F15: =IF(10=0,Assumptions!C9,'10-Year Model'!M29) -> 669485.8

Sheet Executive Verdict
B2: Executive Investment Verdict
B4: INVESTMENT OVERVIEW
B5: This model evaluates a CAD $1,000,000 Toronto condo acquisition with 20% down ($200,000 equity + ~$25,000 closing costs) financed at 6% over 30 years. The property generates $4,000/month gross rent with 10% vacancy and 25% operating expense assumptions.
B7: MARKET ASSESSMENT
B8: The Toronto condo market is emerging from a significant correction (2023–2025) with GTA average condo prices down 5.1% YoY to $652,945 as of Q4 2025 (TRREB). Key dynamics include: record condo completions (31,422 units in 2025) creating near-term oversupply, construction starts at the lowest level since 1998 signaling a future supply cliff, rents declining 6.0% YoY, and investor demand down 95% from 2021 peak. The consensus among major institutions (RBC, TD, BMO, CMHC) is that 2025 represents the trough with modest stabilization in 2026–2027 and gradual recovery thereafter.
B10: SCENARIO ANALYSIS SUMMARY
B11: Base Case (2.5% CAGR): Reflects gradual recovery constrained by structural headwinds. Year 10 property value of ~$1,280,000. The investment generates negative annual cash flow throughout the hold period due to high debt service relative to rental income, but builds substantial equity through principal paydown and appreciation.
B12: Bull Case (4.0% CAGR): Assumes faster supply absorption, immigration policy reversal, and rate cuts. Year 10 property value of ~$1,480,000. Significantly higher equity returns.
B13: Bear Case (0.5% CAGR): Prolonged stagnation with investor exit and recession risk. Year 10 property value of ~$1,051,000. Minimal appreciation; returns driven primarily by principal paydown.
B15: KEY RISKS
B16: 1) Negative cash flow: At 6% mortgage rate, annual debt service exceeds NOI, requiring ongoing capital infusion (~$2,000+/month shortfall). 2) Interest rate sensitivity: Each 50bps increase in mortgage rate reduces cash flow by ~$2,500/year. 3) Oversupply risk: 31,000+ units completing in 2025 may prolong price weakness beyond base case assumptions. 4) Rent stagnation: Declining rents (-6% YoY) and rising vacancy (3.2%–4.0%) limit income growth. 5) Investor sentiment: With 95% decline in pre-construction sales, market recovery depends on restoring investor confidence.
B18: VERDICT
B19: CONDITIONAL HOLD — NOT RECOMMENDED FOR CASH-FLOW-FOCUSED INVESTORS. The investment is viable only for investors with: (a) sufficient liquidity to fund negative cash flow over 10 years (~$200K+ cumulative shortfall), (b) conviction in long-term Toronto appreciation driven by the emerging supply cliff, and (c) tolerance for 3–5 years of flat or declining property values before recovery materializes. For investors seeking positive cash flow or defensive positioning, this investment does not meet hurdle rates at current pricing and interest rates. The base case IRR is modest relative to the risk assumed, and the bear case represents real capital loss. Consider re-evaluating if: mortgage rates fall below 4.5%, purchase price achieves further 10–15% discount, or rents recover to support positive cash flow.
